[
  {
    "type": "constructor",
    "inputs": [
      {
        "name": "blocksToAct",
        "type": "uint256",
        "internalType": "uint256"
      },
      {
        "name": "costToSpin",
        "type": "uint256",
        "internalType": "uint256"
      },
      {
        "name": "costToRespin",
        "type": "uint256",
        "internalType": "uint256"
      }
    ],
    "stateMutability": "nonpayable"
  },
  {
    "type": "receive",
    "stateMutability": "payable"
  },
  {
    "type": "function",
    "name": "BlocksToAct",
    "inputs": [],
    "outputs": [
      {
        "name": "",
        "type": "uint256",
        "internalType": "uint256"
      }
    ],
    "stateMutability": "view"
  },
  {
    "type": "function",
    "name": "CostToRespin",
    "inputs": [],
    "outputs": [
      {
        "name": "",
        "type": "uint256",
        "internalType": "uint256"
      }
    ],
    "stateMutability": "view"
  },
  {
    "type": "function",
    "name": "CostToSpin",
    "inputs": [],
    "outputs": [
      {
        "name": "",
        "type": "uint256",
        "internalType": "uint256"
      }
    ],
    "stateMutability": "view"
  },
  {
    "type": "function",
    "name": "DailyStreakReward",
    "inputs": [],
    "outputs": [
      {
        "name": "",
        "type": "uint256",
        "internalType": "uint256"
      }
    ],
    "stateMutability": "view"
  },
  {
    "type": "function",
    "name": "ImprovedCenterReel",
    "inputs": [
      {
        "name": "",
        "type": "uint256",
        "internalType": "uint256"
      }
    ],
    "outputs": [
      {
        "name": "",
        "type": "uint256",
        "internalType": "uint256"
      }
    ],
    "stateMutability": "view"
  },
  {
    "type": "function",
    "name": "ImprovedLeftReel",
    "inputs": [
      {
        "name": "",
        "type": "uint256",
        "internalType": "uint256"
      }
    ],
    "outputs": [
      {
        "name": "",
        "type": "uint256",
        "internalType": "uint256"
      }
    ],
    "stateMutability": "view"
  },
  {
    "type": "function",
    "name": "ImprovedRightReel",
    "inputs": [
      {
        "name": "",
        "type": "uint256",
        "internalType": "uint256"
      }
    ],
    "outputs": [
      {
        "name": "",
        "type": "uint256",
        "internalType": "uint256"
      }
    ],
    "stateMutability": "view"
  },
  {
    "type": "function",
    "name": "LastSpinBlock",
    "inputs": [
      {
        "name": "",
        "type": "address",
        "internalType": "address"
      }
    ],
    "outputs": [
      {
        "name": "",
        "type": "uint256",
        "internalType": "uint256"
      }
    ],
    "stateMutability": "view"
  },
  {
    "type": "function",
    "name": "LastSpinBoosted",
    "inputs": [
      {
        "name": "",
        "type": "address",
        "internalType": "address"
      }
    ],
    "outputs": [
      {
        "name": "",
        "type": "bool",
        "internalType": "bool"
      }
    ],
    "stateMutability": "view"
  },
  {
    "type": "function",
    "name": "LastStreakDay",
    "inputs": [
      {
        "name": "",
        "type": "address",
        "internalType": "address"
      }
    ],
    "outputs": [
      {
        "name": "",
        "type": "uint256",
        "internalType": "uint256"
      }
    ],
    "stateMutability": "view"
  },
  {
    "type": "function",
    "name": "LastStreakWeek",
    "inputs": [
      {
        "name": "",
        "type": "address",
        "internalType": "address"
      }
    ],
    "outputs": [
      {
        "name": "",
        "type": "uint256",
        "internalType": "uint256"
      }
    ],
    "stateMutability": "view"
  },
  {
    "type": "function",
    "name": "UnmodifiedCenterReel",
    "inputs": [
      {
        "name": "",
        "type": "uint256",
        "internalType": "uint256"
      }
    ],
    "outputs": [
      {
        "name": "",
        "type": "uint256",
        "internalType": "uint256"
      }
    ],
    "stateMutability": "view"
  },
  {
    "type": "function",
    "name": "UnmodifiedLeftReel",
    "inputs": [
      {
        "name": "",
        "type": "uint256",
        "internalType": "uint256"
      }
    ],
    "outputs": [
      {
        "name": "",
        "type": "uint256",
        "internalType": "uint256"
      }
    ],
    "stateMutability": "view"
  },
  {
    "type": "function",
    "name": "UnmodifiedRightReel",
    "inputs": [
      {
        "name": "",
        "type": "uint256",
        "internalType": "uint256"
      }
    ],
    "outputs": [
      {
        "name": "",
        "type": "uint256",
        "internalType": "uint256"
      }
    ],
    "stateMutability": "view"
  },
  {
    "type": "function",
    "name": "WeeklyStreakReward",
    "inputs": [],
    "outputs": [
      {
        "name": "",
        "type": "uint256",
        "internalType": "uint256"
      }
    ],
    "stateMutability": "view"
  },
  {
    "type": "function",
    "name": "accept",
    "inputs": [],
    "outputs": [
      {
        "name": "left",
        "type": "uint256",
        "internalType": "uint256"
      },
      {
        "name": "center",
        "type": "uint256",
        "internalType": "uint256"
      },
      {
        "name": "right",
        "type": "uint256",
        "internalType": "uint256"
      },
      {
        "name": "remainingEntropy",
        "type": "uint256",
        "internalType": "uint256"
      },
      {
        "name": "prize",
        "type": "uint256",
        "internalType": "uint256"
      }
    ],
    "stateMutability": "nonpayable"
  },
  {
    "type": "function",
    "name": "allowance",
    "inputs": [
      {
        "name": "owner",
        "type": "address",
        "internalType": "address"
      },
      {
        "name": "spender",
        "type": "address",
        "internalType": "address"
      }
    ],
    "outputs": [
      {
        "name": "",
        "type": "uint256",
        "internalType": "uint256"
      }
    ],
    "stateMutability": "view"
  },
  {
    "type": "function",
    "name": "approve",
    "inputs": [
      {
        "name": "spender",
        "type": "address",
        "internalType": "address"
      },
      {
        "name": "value",
        "type": "uint256",
        "internalType": "uint256"
      }
    ],
    "outputs": [
      {
        "name": "",
        "type": "bool",
        "internalType": "bool"
      }
    ],
    "stateMutability": "nonpayable"
  },
  {
    "type": "function",
    "name": "balanceOf",
    "inputs": [
      {
        "name": "account",
        "type": "address",
        "internalType": "address"
      }
    ],
    "outputs": [
      {
        "name": "",
        "type": "uint256",
        "internalType": "uint256"
      }
    ],
    "stateMutability": "view"
  },
  {
    "type": "function",
    "name": "decimals",
    "inputs": [],
    "outputs": [
      {
        "name": "",
        "type": "uint8",
        "internalType": "uint8"
      }
    ],
    "stateMutability": "pure"
  },
  {
    "type": "function",
    "name": "inspectEntropy",
    "inputs": [
      {
        "name": "degenerate",
        "type": "address",
        "internalType": "address"
      }
    ],
    "outputs": [
      {
        "name": "",
        "type": "uint256",
        "internalType": "uint256"
      }
    ],
    "stateMutability": "view"
  },
  {
    "type": "function",
    "name": "inspectOutcome",
    "inputs": [
      {
        "name": "degenerate",
        "type": "address",
        "internalType": "address"
      }
    ],
    "outputs": [
      {
        "name": "left",
        "type": "uint256",
        "internalType": "uint256"
      },
      {
        "name": "center",
        "type": "uint256",
        "internalType": "uint256"
      },
      {
        "name": "right",
        "type": "uint256",
        "internalType": "uint256"
      },
      {
        "name": "remainingEntropy",
        "type": "uint256",
        "internalType": "uint256"
      },
      {
        "name": "prize",
        "type": "uint256",
        "internalType": "uint256"
      }
    ],
    "stateMutability": "view"
  },
  {
    "type": "function",
    "name": "latestEntropy",
    "inputs": [
      {
        "name": "degenerate",
        "type": "address",
        "internalType": "address"
      }
    ],
    "outputs": [
      {
        "name": "",
        "type": "uint256",
        "internalType": "uint256"
      }
    ],
    "stateMutability": "view"
  },
  {
    "type": "function",
    "name": "name",
    "inputs": [],
    "outputs": [
      {
        "name": "",
        "type": "string",
        "internalType": "string"
      }
    ],
    "stateMutability": "view"
  },
  {
    "type": "function",
    "name": "outcome",
    "inputs": [
      {
        "name": "entropy",
        "type": "uint256",
        "internalType": "uint256"
      },
      {
        "name": "boosted",
        "type": "bool",
        "internalType": "bool"
      }
    ],
    "outputs": [
      {
        "name": "left",
        "type": "uint256",
        "internalType": "uint256"
      },
      {
        "name": "center",
        "type": "uint256",
        "internalType": "uint256"
      },
      {
        "name": "right",
        "type": "uint256",
        "internalType": "uint256"
      },
      {
        "name": "remainingEntropy",
        "type": "uint256",
        "internalType": "uint256"
      }
    ],
    "stateMutability": "view"
  },
  {
    "type": "function",
    "name": "payout",
    "inputs": [
      {
        "name": "left",
        "type": "uint256",
        "internalType": "uint256"
      },
      {
        "name": "center",
        "type": "uint256",
        "internalType": "uint256"
      },
      {
        "name": "right",
        "type": "uint256",
        "internalType": "uint256"
      }
    ],
    "outputs": [
      {
        "name": "result",
        "type": "uint256",
        "internalType": "uint256"
      }
    ],
    "stateMutability": "view"
  },
  {
    "type": "function",
    "name": "sampleImprovedCenterReel",
    "inputs": [
      {
        "name": "entropy",
        "type": "uint256",
        "internalType": "uint256"
      }
    ],
    "outputs": [
      {
        "name": "",
        "type": "uint256",
        "internalType": "uint256"
      }
    ],
    "stateMutability": "view"
  },
  {
    "type": "function",
    "name": "sampleImprovedLeftReel",
    "inputs": [
      {
        "name": "entropy",
        "type": "uint256",
        "internalType": "uint256"
      }
    ],
    "outputs": [
      {
        "name": "",
        "type": "uint256",
        "internalType": "uint256"
      }
    ],
    "stateMutability": "view"
  },
  {
    "type": "function",
    "name": "sampleImprovedRightReel",
    "inputs": [
      {
        "name": "entropy",
        "type": "uint256",
        "internalType": "uint256"
      }
    ],
    "outputs": [
      {
        "name": "",
        "type": "uint256",
        "internalType": "uint256"
      }
    ],
    "stateMutability": "view"
  },
  {
    "type": "function",
    "name": "sampleUnmodifiedCenterReel",
    "inputs": [
      {
        "name": "entropy",
        "type": "uint256",
        "internalType": "uint256"
      }
    ],
    "outputs": [
      {
        "name": "",
        "type": "uint256",
        "internalType": "uint256"
      }
    ],
    "stateMutability": "view"
  },
  {
    "type": "function",
    "name": "sampleUnmodifiedLeftReel",
    "inputs": [
      {
        "name": "entropy",
        "type": "uint256",
        "internalType": "uint256"
      }
    ],
    "outputs": [
      {
        "name": "",
        "type": "uint256",
        "internalType": "uint256"
      }
    ],
    "stateMutability": "view"
  },
  {
    "type": "function",
    "name": "sampleUnmodifiedRightReel",
    "inputs": [
      {
        "name": "entropy",
        "type": "uint256",
        "internalType": "uint256"
      }
    ],
    "outputs": [
      {
        "name": "",
        "type": "uint256",
        "internalType": "uint256"
      }
    ],
    "stateMutability": "view"
  },
  {
    "type": "function",
    "name": "spin",
    "inputs": [
      {
        "name": "boost",
        "type": "bool",
        "internalType": "bool"
      }
    ],
    "outputs": [],
    "stateMutability": "payable"
  },
  {
    "type": "function",
    "name": "spinCost",
    "inputs": [
      {
        "name": "degenerate",
        "type": "address",
        "internalType": "address"
      }
    ],
    "outputs": [
      {
        "name": "",
        "type": "uint256",
        "internalType": "uint256"
      }
    ],
    "stateMutability": "view"
  },
  {
    "type": "function",
    "name": "supportsInterface",
    "inputs": [
      {
        "name": "interfaceID",
        "type": "bytes4",
        "internalType": "bytes4"
      }
    ],
    "outputs": [
      {
        "name": "",
        "type": "bool",
        "internalType": "bool"
      }
    ],
    "stateMutability": "pure"
  },
  {
    "type": "function",
    "name": "symbol",
    "inputs": [],
    "outputs": [
      {
        "name": "",
        "type": "string",
        "internalType": "string"
      }
    ],
    "stateMutability": "view"
  },
  {
    "type": "function",
    "name": "totalSupply",
    "inputs": [],
    "outputs": [
      {
        "name": "",
        "type": "uint256",
        "internalType": "uint256"
      }
    ],
    "stateMutability": "view"
  },
  {
    "type": "function",
    "name": "transfer",
    "inputs": [
      {
        "name": "to",
        "type": "address",
        "internalType": "address"
      },
      {
        "name": "value",
        "type": "uint256",
        "internalType": "uint256"
      }
    ],
    "outputs": [
      {
        "name": "",
        "type": "bool",
        "internalType": "bool"
      }
    ],
    "stateMutability": "nonpayable"
  },
  {
    "type": "function",
    "name": "transferFrom",
    "inputs": [
      {
        "name": "from",
        "type": "address",
        "internalType": "address"
      },
      {
        "name": "to",
        "type": "address",
        "internalType": "address"
      },
      {
        "name": "value",
        "type": "uint256",
        "internalType": "uint256"
      }
    ],
    "outputs": [
      {
        "name": "",
        "type": "bool",
        "internalType": "bool"
      }
    ],
    "stateMutability": "nonpayable"
  },
  {
    "type": "event",
    "name": "Approval",
    "inputs": [
      {
        "name": "owner",
        "type": "address",
        "indexed": true,
        "internalType": "address"
      },
      {
        "name": "spender",
        "type": "address",
        "indexed": true,
        "internalType": "address"
      },
      {
        "name": "value",
        "type": "uint256",
        "indexed": false,
        "internalType": "uint256"
      }
    ],
    "anonymous": false
  },
  {
    "type": "event",
    "name": "Award",
    "inputs": [
      {
        "name": "player",
        "type": "address",
        "indexed": true,
        "internalType": "address"
      },
      {
        "name": "value",
        "type": "uint256",
        "indexed": false,
        "internalType": "uint256"
      }
    ],
    "anonymous": false
  },
  {
    "type": "event",
    "name": "DailyStreak",
    "inputs": [
      {
        "name": "player",
        "type": "address",
        "indexed": true,
        "internalType": "address"
      },
      {
        "name": "day",
        "type": "uint256",
        "indexed": false,
        "internalType": "uint256"
      }
    ],
    "anonymous": false
  },
  {
    "type": "event",
    "name": "Spin",
    "inputs": [
      {
        "name": "player",
        "type": "address",
        "indexed": true,
        "internalType": "address"
      },
      {
        "name": "bonus",
        "type": "bool",
        "indexed": true,
        "internalType": "bool"
      }
    ],
    "anonymous": false
  },
  {
    "type": "event",
    "name": "Transfer",
    "inputs": [
      {
        "name": "from",
        "type": "address",
        "indexed": true,
        "internalType": "address"
      },
      {
        "name": "to",
        "type": "address",
        "indexed": true,
        "internalType": "address"
      },
      {
        "name": "value",
        "type": "uint256",
        "indexed": false,
        "internalType": "uint256"
      }
    ],
    "anonymous": false
  },
  {
    "type": "event",
    "name": "WeeklyStreak",
    "inputs": [
      {
        "name": "player",
        "type": "address",
        "indexed": true,
        "internalType": "address"
      },
      {
        "name": "week",
        "type": "uint256",
        "indexed": false,
        "internalType": "uint256"
      }
    ],
    "anonymous": false
  },
  {
    "type": "error",
    "name": "DeadlineExceeded",
    "inputs": []
  },
  {
    "type": "error",
    "name": "ERC20InsufficientAllowance",
    "inputs": [
      {
        "name": "spender",
        "type": "address",
        "internalType": "address"
      },
      {
        "name": "allowance",
        "type": "uint256",
        "internalType": "uint256"
      },
      {
        "name": "needed",
        "type": "uint256",
        "internalType": "uint256"
      }
    ]
  },
  {
    "type": "error",
    "name": "ERC20InsufficientBalance",
    "inputs": [
      {
        "name": "sender",
        "type": "address",
        "internalType": "address"
      },
      {
        "name": "balance",
        "type": "uint256",
        "internalType": "uint256"
      },
      {
        "name": "needed",
        "type": "uint256",
        "internalType": "uint256"
      }
    ]
  },
  {
    "type": "error",
    "name": "ERC20InvalidApprover",
    "inputs": [
      {
        "name": "approver",
        "type": "address",
        "internalType": "address"
      }
    ]
  },
  {
    "type": "error",
    "name": "ERC20InvalidReceiver",
    "inputs": [
      {
        "name": "receiver",
        "type": "address",
        "internalType": "address"
      }
    ]
  },
  {
    "type": "error",
    "name": "ERC20InvalidSender",
    "inputs": [
      {
        "name": "sender",
        "type": "address",
        "internalType": "address"
      }
    ]
  },
  {
    "type": "error",
    "name": "ERC20InvalidSpender",
    "inputs": [
      {
        "name": "spender",
        "type": "address",
        "internalType": "address"
      }
    ]
  },
  {
    "type": "error",
    "name": "InsufficientValue",
    "inputs": []
  },
  {
    "type": "error",
    "name": "OutcomeOutOfBounds",
    "inputs": []
  },
  {
    "type": "error",
    "name": "ReentrancyGuardReentrantCall",
    "inputs": []
  },
  {
    "type": "error",
    "name": "WaitForTick",
    "inputs": []
  }
]
